file_fuse/__init__.py
file_fuse/file_fuse.py
fileFuse-0.0.1.dist-info/LICENSE
fileFuse-0.0.1.dist-info/METADATA
fileFuse-0.0.1.dist-info/WHEEL
fileFuse-0.0.1.dist-info/top_level.txt
fileFuse-0.0.1.dist-info/RECORD
