Metadata-Version: 2.1
Name: fileFuse
Version: 0.0.1
Summary: This project is used to read a file and return the contents of the file
Home-page: https://github.com/jayantkhanna1/fileFuse
Author: Jayant Khanna
Author-email: jayantkhanna3105@gmail.com
Classifier: Programming Language :: Python :: 3
Classifier: Operating System :: OS Independent
Requires-Python: >=3.7
License-File: LICENSE
